tang_yuan_mlops_sdk/__init__.py
tang_yuan_mlops_sdk/config.py
tang_yuan_mlops_sdk/exceptions.py
tang_yuan_mlops_sdk/version.py
tang_yuan_mlops_sdk/core/__init__.py
tang_yuan_mlops_sdk/core/http_client.py
tang_yuan_mlops_sdk/llm/__init__.py
tang_yuan_mlops_sdk/llm/embedding.py
tang_yuan_mlops_sdk/llm/rerank.py
tang_yuan_mlops_sdk/voice/__init__.py
tang_yuan_mlops_sdk/voice/asr.py
tang_yuan_mlops_sdk/voice/tts.py
tests/__init__.py
tests/test_llm_embedding.py
tests/test_llm_rerank.py
tests/test_voice_asr.py
tests/test_voice_tts.py
tang_yuan_mlops_sdk-0.1.3.dist-info/METADATA
tang_yuan_mlops_sdk-0.1.3.dist-info/WHEEL
tang_yuan_mlops_sdk-0.1.3.dist-info/top_level.txt
tang_yuan_mlops_sdk-0.1.3.dist-info/RECORD
