Metadata-Version: 2.2
Name: tang-yuan-mlops-sdk
Version: 0.1.3
Summary: A MLOps SDK example with LLM & Voice modules
Author: YourTeam
Author-email: 17348241417@163.com
Classifier: Programming Language :: Python :: 3.12
Classifier: Operating System :: OS Independent
Requires-Python: >=3.12
Requires-Dist: scipy~=1.15.2
Dynamic: author
Dynamic: author-email
Dynamic: classifier
Dynamic: description
Dynamic: description-content-type
Dynamic: requires-dist
Dynamic: requires-python
Dynamic: summary
